LICENSE.txt
MANIFEST.in
README.rst
Tool.py
setup.py
yutest/__init__.py
yutest/yutest.py
yutest.egg-info/PKG-INFO
yutest.egg-info/SOURCES.txt
yutest.egg-info/dependency_links.txt
yutest.egg-info/top_level.txt