Metadata-Version: 1.0
Name: yutest
Version: 1.0.1
Summary: 这是一个牛逼的库
Home-page: https://github.com/AoXinYu/yutest/
Author: yu
Author-email: yua5726@gmail.com
License: UNKNOWN
Platform: UNKNOWN
